{
        "list":{
                "美团红包":"  每天可以领，吃饭更便宜",
                "饿了么红包":"  每天可以领，吃饭更便宜",
                "更多淘宝活动":"显示更多的淘宝活动"
            },
        "mapping" :{
            "美团红包":{
                "url":"tbopen://"
            },
            "饿了么红包":{
                "url":"tbopen://"
            },
            "更多淘宝活动":{
                "list":{
                    "活动1里的活动1":"618红包"
                },
                "mapping":{
                    "活动1里的活动1":{
                        "url":"tbopen://"
                    }
                }
            }
        }
            
}
